treeline/__init__.py
treeline/analyzer.py
treeline/cli.py
treeline/core.py
treeline/main.py
treeline/renderer.py
treeline/utils.py
treeline-1.0.1.dist-info/METADATA
treeline-1.0.1.dist-info/WHEEL
treeline-1.0.1.dist-info/entry_points.txt
treeline-1.0.1.dist-info/top_level.txt
treeline-1.0.1.dist-info/RECORD
