Metadata-Version: 2.4
Name: treeline
Version: 1.0.1
Summary: Enhanced tree command with code structure analysis
Author-email: oha <aaronoh2015@gmail.com>
License: MIT
Project-URL: Homepage, https://github.com/duriantaco/treeline
Requires-Python: >=3.7
Requires-Dist: click>=8.0.0
Requires-Dist: rich>=10.0.0
